pypushover_logger/__init__.py
pypushover_logger-0.1.0.dist-info/LICENSE
pypushover_logger-0.1.0.dist-info/WHEEL
pypushover_logger-0.1.0.dist-info/METADATA
pypushover_logger-0.1.0.dist-info/RECORD
