Metadata-Version: 2.1
Name: pypushover-logger
Version: 0.1.0
Summary: A Pushover logging handler
Author: Jeffrey Muller
Author-email: jeffrey.muller92@gmail.com
Requires-Python: >=3.9,<4.0
Classifier: Programming Language :: Python :: 3
Classifier: Programming Language :: Python :: 3.9
Classifier: Programming Language :: Python :: 3.10
Classifier: Programming Language :: Python :: 3.11
